__init__.py
axray/__init__.py
axray/tracker.py
artefacts_xray-0.2.0.dist-info/METADATA
artefacts_xray-0.2.0.dist-info/WHEEL
artefacts_xray-0.2.0.dist-info/top_level.txt
artefacts_xray-0.2.0.dist-info/RECORD
