Metadata-Version: 2.4
Name: artefacts-xray
Version: 0.2.0
Summary: Add your description here
Requires-Python: >=3.10
Requires-Dist: memory-profiler>=0.61.0
Requires-Dist: numpy
Requires-Dist: psutil>=7.0.0
Requires-Dist: pytest-mock>=3.15.1
Requires-Dist: terminaltables>=3.1.10
